[
  [
    {
      "Attempt No.": "1",
      "Ink": "Implant  Blocker V1 1x used",
      "layer height [µm]": "0.1",
      "no. bottom layers": "1",
      "texp.bottom  [s]": "25",
      "texposure_pos1 [s]": "12",
      "texposure_pos2 [s]": "",
      "texposure_pos3 [s]": "",
      "texposure_pos4 [s]": "",
      "zSpeed": "15",
      "status": "Success",
      "comment": "3 mL, Pause after layer 15: good prints, some edges are not smooth, +1 mL ink, esposure time of layer 15-30 incresed to 13 sec, continued, Pause after layer 30: super prints, +1 mL ink & exposure time of layer 30-70 incresed to 1 s--> continue, Pause after layer 62 (it looked liked prints detached, but didn't) --> continue, final prints: super prints, but a few layers attached to FEP film (probably the ones after the pause at layer 62, should not make a huge difference) -> transferred into warm DPBS, then 45 min FormCure at 38°C",
      "next steps": "All layers after 1st --> exposure time to 13  sec",
      "pictures": ""
    },
    {
      "Attempt No.": "2",
      "Ink": "",
      "layer height [µm]": "",
      "no. bottom layers": "",
      "texp.bottom  [s]": "",
      "texposure_pos1 [s]": "13",
      "texposure_pos2 [s]": "",
      "texposure_pos3 [s]": "",
      "texposure_pos4 [s]": "",
      "zSpeed": "",
      "status": "Success",
      "comment": "4 mL, Pause after layer 30: super prints -> continue, too much ink in the beginning --> spreaded across FEP film and outer parts gelled because of temp. pause after layer 50: super prints, + ca 400 µL ink (rest), continue, final prints: super! In warm DPBS, Formcure until not yellow anymore, not enough ink for next print",
      "next steps": "",
      "pictures": ""
    },
    {
      "Attempt No.": "3",
      "Ink": "Implant  Blocker V1 220615MF",
      "layer height [µm]": "",
      "no. bottom layers": "",
      "texp.bottom  [s]": "",
      "texposure_pos1 [s]": "",
      "texposure_pos2 [s]": "",
      "texposure_pos3 [s]": "",
      "texposure_pos4 [s]": "",
      "zSpeed": "",
      "status": "fail",
      "comment": "Pause of ~2 h, LuK printed in between time, 3 mL newly prepared ink, Pause after layer 20: prints attacheched to FEP film and ripped appart , airbubble in middle print",
      "next steps": "Reduce exposure time to 12 sec, zHOp to 2.2",
      "pictures": ""
    },
    {
      "Attempt No.": "4",
      "Ink": "",
      "layer height [µm]": "",
      "no. bottom layers": "",
      "texp.bottom  [s]": "",
      "texposure_pos1 [s]": "12",
      "texposure_pos2 [s]": "",
      "texposure_pos3 [s]": "",
      "texposure_pos4 [s]": "",
      "zSpeed": "",
      "status": "fail",
      "comment": "3 mL, Pause after layer 10: prints attached to FEP film but less than before, but prints on printhead werew very soft",
      "next steps": "Incraese exposure time to 13 sec. Turn dish to other side",
      "pictures": ""
    },
    {
      "Attempt No.": "5",
      "Ink": "",
      "layer height [µm]": "",
      "no. bottom layers": "",
      "texp.bottom  [s]": "",
      "texposure_pos1 [s]": "",
      "texposure_pos2 [s]": "",
      "texposure_pos3 [s]": "",
      "texposure_pos4 [s]": "",
      "zSpeed": "",
      "status": "",
      "comment": "3 mL, Pause after layer 10:  prints super soft, edges round, and some bits attached to FEP film, exposure imew was still set to 12 sec, accidentially moved printhead to much down before print --> imprint in FEP film + prints turned out super flat Restart system",
      "next steps": "increase exposure time to 14 sec",
      "pictures": ""
    },
    {
      "Attempt No.": "6",
      "Ink": "",
      "layer height [µm]": "",
      "no. bottom layers": "",
      "texp.bottom  [s]": "",
      "texposure_pos1 [s]": "14",
      "texposure_pos2 [s]": "",
      "texposure_pos3 [s]": "",
      "texposure_pos4 [s]": "",
      "zSpeed": "",
      "status": "",
      "comment": "accidentially moved printhead to much down before print --> imprint in FEP film + prints turned out super flat Restart system",
      "next steps": "",
      "pictures": ""
    },
    {
      "Attempt No.": "7",
      "Ink": "",
      "layer height [µm]": "",
      "no. bottom layers": "",
      "texp.bottom  [s]": "",
      "texposure_pos1 [s]": "",
      "texposure_pos2 [s]": "",
      "texposure_pos3 [s]": "",
      "texposure_pos4 [s]": "",
      "zSpeed": "",
      "status": "",
      "comment": "3 mL, Pause after layer 10: prints okay, continue, Pause after layer 31:prints attached to FEP Film",
      "next steps": "Reduce exposure time to 12.5 sec, zHOP to 2.5",
      "pictures": ""
    },
    {
      "Attempt No.": "8",
      "Ink": "",
      "layer height [µm]": "",
      "no. bottom layers": "",
      "texp.bottom  [s]": "",
      "texposure_pos1 [s]": "12.5",
      "texposure_pos2 [s]": "",
      "texposure_pos3 [s]": "",
      "texposure_pos4 [s]": "",
      "zSpeed": "",
      "status": "",
      "comment": "3 mL, Pause after layer 10: prints very soft and bad defined -> increase exposure time to 13.5, continue, pause aftler layer 30: prints have bad shape (increse exposure time), light circle in Vat visible but nothing attached, + 1 mL 1x used ink, continue, final prints: attached to dish, but one, the one print was badly defined and very soft, upper and lower cylinder barely connected",
      "next steps": "zHOP to 3, exposure time to 14 sec",
      "pictures": ""
    }
  ]
]