[
  [
    {
      "Attempt No.": "1",
      "Ink": "T1-230327",
      "layer height [µm]": "500",
      "no. bottom layers": "",
      "texp.bottom  [s]": "",
      "texposure_pos1 [s]": "12 12 12 12",
      "texposure_pos2 [s]": "/",
      "texposure_pos3 [s]": "/",
      "texposure_pos4 [s]": "/",
      "zSpeed": "50",
      "status": "",
      "comment": "Offset: -1.4 ok but 1st layer a bit soft - disolves a bit when removing from print head No big overcuring - to the eye not visible",
      "next steps": "Position in VAT is changed Printhead is cleaned New ink is imployed Exposure time of first layer is raised to 14s, rest is kept at 12s",
      "pictures": ""
    },
    {
      "Attempt No.": "2",
      "Ink": "T1-230327",
      "layer height [µm]": "500",
      "no. bottom layers": "",
      "texp.bottom  [s]": "",
      "texposure_pos1 [s]": "14 12 12 12",
      "texposure_pos2 [s]": "",
      "texposure_pos3 [s]": "",
      "texposure_pos4 [s]": "",
      "zSpeed": "50",
      "status": "",
      "comment": "Overcuring - visible to the naked eye --> 14s is too much --> try 13s next time otherwise stay with 12s and be extremely careful when removing",
      "next steps": "",
      "pictures": ""
    },
    {
      "Attempt No.": "3",
      "Ink": "",
      "layer height [µm]": "",
      "no. bottom layers": "",
      "texp.bottom  [s]": "",
      "texposure_pos1 [s]": "",
      "texposure_pos2 [s]": "",
      "texposure_pos3 [s]": "",
      "texposure_pos4 [s]": "",
      "zSpeed": "",
      "status": "",
      "comment": "",
      "next steps": "",
      "pictures": ""
    },
    {
      "Attempt No.": "4",
      "Ink": "",
      "layer height [µm]": "",
      "no. bottom layers": "",
      "texp.bottom  [s]": "",
      "texposure_pos1 [s]": "",
      "texposure_pos2 [s]": "",
      "texposure_pos3 [s]": "",
      "texposure_pos4 [s]": "",
      "zSpeed": "",
      "status": "",
      "comment": "",
      "next steps": "",
      "pictures": ""
    },
    {
      "Attempt No.": "",
      "Ink": "",
      "layer height [µm]": "",
      "no. bottom layers": "",
      "texp.bottom  [s]": "",
      "texposure_pos1 [s]": "",
      "texposure_pos2 [s]": "",
      "texposure_pos3 [s]": "",
      "texposure_pos4 [s]": "",
      "zSpeed": "",
      "status": "",
      "comment": "",
      "next steps": "",
      "pictures": ""
    },
    {
      "Attempt No.": "",
      "Ink": "",
      "layer height [µm]": "",
      "no. bottom layers": "",
      "texp.bottom  [s]": "",
      "texposure_pos1 [s]": "",
      "texposure_pos2 [s]": "",
      "texposure_pos3 [s]": "",
      "texposure_pos4 [s]": "",
      "zSpeed": "",
      "status": "",
      "comment": "",
      "next steps": "",
      "pictures": ""
    },
    {
      "Attempt No.": "",
      "Ink": "",
      "layer height [µm]": "",
      "no. bottom layers": "",
      "texp.bottom  [s]": "",
      "texposure_pos1 [s]": "",
      "texposure_pos2 [s]": "",
      "texposure_pos3 [s]": "",
      "texposure_pos4 [s]": "",
      "zSpeed": "",
      "status": "",
      "comment": "",
      "next steps": "",
      "pictures": ""
    }
  ]
]