[
  [
    {
      "Attempt No.": "1",
      "Ink": "Demo02",
      "layer height [µm]": "100",
      "no. bottom layers": "0",
      "texp.bottom  [s]": "-",
      "texp.layer [s]": "4",
      "zSpeed": "250",
      "status": "fail",
      "comment": "Although visible exposure, no curing, quite dark LED",
      "next steps": "Clean-up",
      "pictures": ""
    },
    {
      "Attempt No.": "2",
      "Ink": "Demo02",
      "layer height [µm]": "100",
      "no. bottom layers": "0",
      "texp.bottom  [s]": "-",
      "texp.layer [s]": "4",
      "zSpeed": "250",
      "status": "success",
      "comment": "All went well",
      "next steps": "Clean-up",
      "pictures": ""
    },
    {
      "Attempt No.": "",
      "Ink": "",
      "layer height [µm]": "",
      "no. bottom layers": "",
      "texp.bottom  [s]": "",
      "texp.layer [s]": "",
      "zSpeed": "",
      "status": "",
      "comment": "",
      "next steps": "",
      "pictures": ""
    }
  ]
]